Metadata-Version: 1.0
Name: spark-notebook-helpers
Version: 1.0.1
Summary: Helper functions for Apache Spark notebooks and demos
Home-page: UNKNOWN
Author: Jon Bates and contributors from Databricks
Author-email: training-logins@databricks.com
License: Creative Commons Attribution-NonCommercial 4.0 International
Keywords: spark,databricks
Platform: UNKNOWN
